[
    {
        "id":  1620,
        "prefecture":  "富山県",
        "city":  "富山市",
        "area":  "水橋北",
        "name":  "富山市水橋北地域包括支援センター",
        "tel":  "076-478-0311",
        "url":  "https://www.city.toyama.lg.jp/health/kourei/1010504/1003641.html"
    },
    {
        "id":  1621,
        "prefecture":  "富山県",
        "city":  "富山市",
        "area":  "水橋南",
        "name":  "富山市水橋南地域包括支援センター",
        "tel":  "076-479-2299",
        "url":  "https://www.city.toyama.lg.jp/health/kourei/1010504/1003641.html"
    },
    {
        "id":  1622,
        "prefecture":  "富山県",
        "city":  "富山市",
        "area":  "大広田・浜黒崎",
        "name":  "富山市大広田・浜黒崎地域包括支援センター",
        "tel":  "076-437-8022",
        "url":  "https://www.city.toyama.lg.jp/health/kourei/1010504/1003641.html"
    },
    {
        "id":  1623,
        "prefecture":  "富山県",
        "city":  "富山市",
        "area":  "岩瀬・萩浦",
        "name":  "富山市岩瀬・萩浦地域包括支援センター",
        "tel":  "076-438-8483",
        "url":  "https://www.city.toyama.lg.jp/health/kourei/1010504/1003641.html"
    },
    {
        "id":  1624,
        "prefecture":  "富山県",
        "city":  "富山市",
        "area":  "和合",
        "name":  "富山市和合地域包括支援センター",
        "tel":  "076-435-0524",
        "url":  "https://www.city.toyama.lg.jp/health/kourei/1010504/1003641.html"
    },
    {
        "id":  1625,
        "prefecture":  "富山県",
        "city":  "富山市",
        "area":  "針原",
        "name":  "富山市針原地域包括支援センター",
        "tel":  "076-451-1200",
        "url":  "https://www.city.toyama.lg.jp/health/kourei/1010504/1003641.html"
    },
    {
        "id":  1626,
        "prefecture":  "富山県",
        "city":  "富山市",
        "area":  "新庄",
        "name":  "富山市新庄地域包括支援センター",
        "tel":  "076-451-8014",
        "url":  "https://www.city.toyama.lg.jp/health/kourei/1010504/1003641.html"
    },
    {
        "id":  1627,
        "prefecture":  "富山県",
        "city":  "富山市",
        "area":  "豊田",
        "name":  "富山市豊田地域包括支援センター",
        "tel":  "076-433-7870",
        "url":  "https://www.city.toyama.lg.jp/health/kourei/1010504/1003641.html"
    },
    {
        "id":  1628,
        "prefecture":  "富山県",
        "city":  "富山市",
        "area":  "広田",
        "name":  "富山市広田地域包括支援センター",
        "tel":  "076-411-0231",
        "url":  "https://www.city.toyama.lg.jp/health/kourei/1010504/1003641.html"
    },
    {
        "id":  1629,
        "prefecture":  "富山県",
        "city":  "富山市",
        "area":  "奥田北",
        "name":  "富山市奥田北地域包括支援センター",
        "tel":  "076-433-8808",
        "url":  "https://www.city.toyama.lg.jp/health/kourei/1010504/1003641.html"
    },
    {
        "id":  1630,
        "prefecture":  "富山県",
        "city":  "富山市",
        "area":  "奥田",
        "name":  "富山市奥田地域包括支援センター",
        "tel":  "076-432-5762",
        "url":  "https://www.city.toyama.lg.jp/health/kourei/1010504/1003641.html"
    },
    {
        "id":  1631,
        "prefecture":  "富山県",
        "city":  "富山市",
        "area":  "百塚",
        "name":  "富山市百塚地域包括支援センター",
        "tel":  "076-433-8266",
        "url":  "https://www.city.toyama.lg.jp/health/kourei/1010504/1003641.html"
    },
    {
        "id":  1632,
        "prefecture":  "富山県",
        "city":  "富山市",
        "area":  "呉羽",
        "name":  "富山市呉羽地域包括支援センター",
        "tel":  "076-436-2117",
        "url":  "https://www.city.toyama.lg.jp/health/kourei/1010504/1003641.html"
    },
    {
        "id":  1633,
        "prefecture":  "富山県",
        "city":  "富山市",
        "area":  "神明・五福",
        "name":  "富山市神明・五福地域包括支援センター",
        "tel":  "076-433-8857",
        "url":  "https://www.city.toyama.lg.jp/health/kourei/1010504/1003641.html"
    },
    {
        "id":  1634,
        "prefecture":  "富山県",
        "city":  "富山市",
        "area":  "愛宕・安野屋",
        "name":  "富山市愛宕・安野屋地域包括支援センター",
        "tel":  "076-433-2405",
        "url":  "https://www.city.toyama.lg.jp/health/kourei/1010504/1003641.html"
    },
    {
        "id":  1635,
        "prefecture":  "富山県",
        "city":  "富山市",
        "area":  "まちなか",
        "name":  "富山市まちなか地域包括支援センター",
        "tel":  "076-461-8151",
        "url":  "https://www.city.toyama.lg.jp/health/kourei/1010504/1003641.html"
    },
    {
        "id":  1636,
        "prefecture":  "富山県",
        "city":  "富山市",
        "area":  "柳町・清水町",
        "name":  "富山市柳町・清水町地域包括支援センター",
        "tel":  "076-492-6611",
        "url":  "https://www.city.toyama.lg.jp/health/kourei/1010504/1003641.html"
    },
    {
        "id":  1637,
        "prefecture":  "富山県",
        "city":  "富山市",
        "area":  "東部・山室",
        "name":  "富山市東部・山室地域包括支援センター",
        "tel":  "076-494-1220",
        "url":  "https://www.city.toyama.lg.jp/health/kourei/1010504/1003641.html"
    },
    {
        "id":  1638,
        "prefecture":  "富山県",
        "city":  "富山市",
        "area":  "藤ノ木・山室中部",
        "name":  "富山市藤ノ木・山室中部地域包括支援センター",
        "tel":  "076-492-3146",
        "url":  "https://www.city.toyama.lg.jp/health/kourei/1010504/1003641.html"
    },
    {
        "id":  1639,
        "prefecture":  "富山県",
        "city":  "富山市",
        "area":  "堀川・光陽",
        "name":  "富山市堀川・光陽地域包括支援センター",
        "tel":  "076-493-9111",
        "url":  "https://www.city.toyama.lg.jp/health/kourei/1010504/1003641.html"
    },
    {
        "id":  1640,
        "prefecture":  "富山県",
        "city":  "富山市",
        "area":  "蜷川",
        "name":  "富山市蜷川地域包括支援センター",
        "tel":  "076-429-6602",
        "url":  "https://www.city.toyama.lg.jp/health/kourei/1010504/1003641.html"
    },
    {
        "id":  1641,
        "prefecture":  "富山県",
        "city":  "富山市",
        "area":  "堀川南",
        "name":  "富山市堀川南地域包括支援センター",
        "tel":  "076-411-7373",
        "url":  "https://www.city.toyama.lg.jp/health/kourei/1010504/1003641.html"
    },
    {
        "id":  1642,
        "prefecture":  "富山県",
        "city":  "富山市",
        "area":  "太田",
        "name":  "富山市太田地域包括支援センター",
        "tel":  "076-422-3283",
        "url":  "https://www.city.toyama.lg.jp/health/kourei/1010504/1003641.html"
    },
    {
        "id":  1643,
        "prefecture":  "富山県",
        "city":  "富山市",
        "area":  "月岡",
        "name":  "富山市月岡地域包括支援センター",
        "tel":  "076-429-7151",
        "url":  "https://www.city.toyama.lg.jp/health/kourei/1010504/1003641.html"
    },
    {
        "id":  1644,
        "prefecture":  "富山県",
        "city":  "富山市",
        "area":  "新保・熊野",
        "name":  "富山市新保・熊野地域包括支援センター",
        "tel":  "076-429-6676",
        "url":  "https://www.city.toyama.lg.jp/health/kourei/1010504/1003641.html"
    },
    {
        "id":  1645,
        "prefecture":  "富山県",
        "city":  "富山市",
        "area":  "大沢野・細入",
        "name":  "富山市大沢野・細入地域包括支援センター",
        "tel":  "076-467-3590",
        "url":  "https://www.city.toyama.lg.jp/health/kourei/1010504/1003641.html"
    },
    {
        "id":  1646,
        "prefecture":  "富山県",
        "city":  "富山市",
        "area":  "大久保・船峅",
        "name":  "富山市大久保・船峅地域包括支援センター",
        "tel":  "076-468-8180",
        "url":  "https://www.city.toyama.lg.jp/health/kourei/1010504/1003641.html"
    },
    {
        "id":  1647,
        "prefecture":  "富山県",
        "city":  "富山市",
        "area":  "大山",
        "name":  "富山市大山地域包括支援センター",
        "tel":  "076-483-4188",
        "url":  "https://www.city.toyama.lg.jp/health/kourei/1010504/1003641.html"
    },
    {
        "id":  1648,
        "prefecture":  "富山県",
        "city":  "富山市",
        "area":  "八尾北・山田",
        "name":  "富山市八尾北・山田地域包括支援センター",
        "tel":  "076-454-6066",
        "url":  "https://www.city.toyama.lg.jp/health/kourei/1010504/1003641.html"
    },
    {
        "id":  1649,
        "prefecture":  "富山県",
        "city":  "富山市",
        "area":  "八尾南",
        "name":  "富山市八尾南地域包括支援センター",
        "tel":  "076-454-5506",
        "url":  "https://www.city.toyama.lg.jp/health/kourei/1010504/1003641.html"
    },
    {
        "id":  1650,
        "prefecture":  "富山県",
        "city":  "富山市",
        "area":  "婦中東",
        "name":  "富山市婦中東地域包括支援センター",
        "tel":  "076-466-0620",
        "url":  "https://www.city.toyama.lg.jp/health/kourei/1010504/1003641.html"
    },
    {
        "id":  1651,
        "prefecture":  "富山県",
        "city":  "富山市",
        "area":  "婦中西",
        "name":  "富山市婦中西地域包括支援センター",
        "tel":  "076-469-1050",
        "url":  "https://www.city.toyama.lg.jp/health/kourei/1010504/1003641.html"
    },
    {
        "id":  2135,
        "prefecture":  "富山県",
        "city":  "高岡市",
        "area":  "伏木・太田",
        "name":  "伏木・太田地域包括支援センター",
        "tel":  "0766-44-7885",
        "url":  "https://www.city.takaoka.toyama.jp/soshiki/koreikaigoka/2/1/5/2432.html"
    },
    {
        "id":  2136,
        "prefecture":  "富山県",
        "city":  "高岡市",
        "area":  "守山・二上・能町",
        "name":  "守山・二上・能町地域包括支援センター",
        "tel":  "0766-25-0809",
        "url":  "https://www.city.takaoka.toyama.jp/soshiki/koreikaigoka/2/1/5/2432.html"
    },
    {
        "id":  2137,
        "prefecture":  "富山県",
        "city":  "高岡市",
        "area":  "牧野",
        "name":  "牧野地域包括支援センター",
        "tel":  "0766-53-5110",
        "url":  "https://www.city.takaoka.toyama.jp/soshiki/koreikaigoka/2/1/5/2432.html"
    },
    {
        "id":  2138,
        "prefecture":  "富山県",
        "city":  "高岡市",
        "area":  "横田・西条・成美",
        "name":  "横田・西条・成美地域包括支援センター",
        "tel":  "0766-27-7363",
        "url":  "https://www.city.takaoka.toyama.jp/soshiki/koreikaigoka/2/1/5/2432.html"
    },
    {
        "id":  2139,
        "prefecture":  "富山県",
        "city":  "高岡市",
        "area":  "野村",
        "name":  "野村地域包括支援センター",
        "tel":  "0766-20-8920",
        "url":  "https://www.city.takaoka.toyama.jp/soshiki/koreikaigoka/2/1/5/2432.html"
    },
    {
        "id":  2140,
        "prefecture":  "富山県",
        "city":  "高岡市",
        "area":  "高陵・下関",
        "name":  "高陵・下関地域包括支援センター",
        "tel":  "0766-26-7062",
        "url":  "https://www.city.takaoka.toyama.jp/soshiki/koreikaigoka/2/1/5/2432.html"
    },
    {
        "id":  2141,
        "prefecture":  "富山県",
        "city":  "高岡市",
        "area":  "博労・川原",
        "name":  "博労・川原地域包括支援センター",
        "tel":  "0766-28-7717",
        "url":  "https://www.city.takaoka.toyama.jp/soshiki/koreikaigoka/2/1/5/2432.html"
    },
    {
        "id":  2142,
        "prefecture":  "富山県",
        "city":  "高岡市",
        "area":  "木津・福田・佐野・二塚",
        "name":  "木津・福田・佐野・二塚地域包括支援センター",
        "tel":  "0766-31-0700",
        "url":  "https://www.city.takaoka.toyama.jp/soshiki/koreikaigoka/2/1/5/2432.html"
    },
    {
        "id":  2143,
        "prefecture":  "富山県",
        "city":  "高岡市",
        "area":  "国吉・五位",
        "name":  "国吉・五位地域包括支援センター",
        "tel":  "0766-50-9251",
        "url":  "https://www.city.takaoka.toyama.jp/soshiki/koreikaigoka/2/1/5/2432.html"
    },
    {
        "id":  2144,
        "prefecture":  "富山県",
        "city":  "高岡市",
        "area":  "戸出・中田",
        "name":  "戸出・中田地域包括支援センター",
        "tel":  "0766-62-1777",
        "url":  "https://www.city.takaoka.toyama.jp/soshiki/koreikaigoka/2/1/5/2432.html"
    },
    {
        "id":  2145,
        "prefecture":  "富山県",
        "city":  "高岡市",
        "area":  "福岡",
        "name":  "福岡地域包括支援センター",
        "tel":  "0766-64-1186",
        "url":  "https://www.city.takaoka.toyama.jp/soshiki/koreikaigoka/2/1/5/2432.html"
    },
    {
        "id":  2999,
        "prefecture":  "富山県",
        "city":  "射水市",
        "area":  "庄西町・港町・庄川本町・本町一〜三丁目・放生津町・中央町・桜町・西新湊・三日曽根・善光寺・緑町・塚原地区・作道地区",
        "name":  "新湊西地域包括支援センター",
        "tel":  "0766-83-7171",
        "url":  "https://www.city.imizu.toyama.jp/guide/svguidedtl.aspx?servno=5482"
    },
    {
        "id":  3000,
        "prefecture":  "富山県",
        "city":  "射水市",
        "area":  "立町・八幡町一〜三丁目・中新湊・二の丸町・越の潟町・海王町・片口地区・堀岡地区・海老江地区・本江地区・七美地区",
        "name":  "新湊東地域包括支援センター",
        "tel":  "0766-86-8739",
        "url":  "https://www.city.imizu.toyama.jp/guide/svguidedtl.aspx?servno=5482"
    },
    {
        "id":  3001,
        "prefecture":  "富山県",
        "city":  "射水市",
        "area":  "三ケ地区・戸破地区・大江地区・下地区",
        "name":  "小杉・下地域包括支援センター",
        "tel":  "0766-55-8217",
        "url":  "https://www.city.imizu.toyama.jp/guide/svguidedtl.aspx?servno=5482"
    },
    {
        "id":  3002,
        "prefecture":  "富山県",
        "city":  "射水市",
        "area":  "橋下条地区・金山地区・黒河地区・池多地区・太閤山地区・中太閤山地区・南太閤山地区",
        "name":  "小杉南地域包括支援センター",
        "tel":  "0766-56-8725",
        "url":  "https://www.city.imizu.toyama.jp/guide/svguidedtl.aspx?servno=5482"
    },
    {
        "id":  3003,
        "prefecture":  "富山県",
        "city":  "射水市",
        "area":  "浅井地区・櫛田地区・水戸田地区・二口地区・大門地区",
        "name":  "大門地域包括支援センター",
        "tel":  "0766-52-0800",
        "url":  "https://www.city.imizu.toyama.jp/guide/svguidedtl.aspx?servno=5482"
    },
    {
        "id":  3004,
        "prefecture":  "富山県",
        "city":  "射水市",
        "area":  "大島地区",
        "name":  "大島地域包括支援センター",
        "tel":  "0766-52-8050",
        "url":  "https://www.city.imizu.toyama.jp/guide/svguidedtl.aspx?servno=5482"
    }
]