[
    {
        "id":  1681,
        "prefecture":  "山口県",
        "city":  "山口市",
        "area":  "大殿・白石・湯田",
        "name":  "山口市中央地域包括支援センター",
        "tel":  "083-934-3338",
        "url":  "https://www.city.yamaguchi.lg.jp/site/korei/4741.html"
    },
    {
        "id":  1682,
        "prefecture":  "山口県",
        "city":  "山口市",
        "area":  "小鯖・大内",
        "name":  "山口市北東地域包括支援センター",
        "tel":  "083-941-6672",
        "url":  "https://www.city.yamaguchi.lg.jp/site/korei/4741.html"
    },
    {
        "id":  1683,
        "prefecture":  "山口県",
        "city":  "山口市",
        "area":  "仁保・宮野",
        "name":  "山口市北東第２地域包括支援センター",
        "tel":  "083-929-1414",
        "url":  "https://www.city.yamaguchi.lg.jp/site/korei/4741.html"
    },
    {
        "id":  1684,
        "prefecture":  "山口県",
        "city":  "山口市",
        "area":  "吉敷・平川・大歳",
        "name":  "山口市鴻南地域包括支援センター",
        "tel":  "083-934-3333",
        "url":  "https://www.city.yamaguchi.lg.jp/site/korei/4741.html"
    },
    {
        "id":  1685,
        "prefecture":  "山口県",
        "city":  "山口市",
        "area":  "小郡",
        "name":  "山口市川西地域包括支援センター",
        "tel":  "083-976-5711",
        "url":  "https://www.city.yamaguchi.lg.jp/site/korei/4741.html"
    },
    {
        "id":  1686,
        "prefecture":  "山口県",
        "city":  "山口市",
        "area":  "嘉川・佐山・阿知須",
        "name":  "山口市川西第２地域包括支援センター",
        "tel":  "0836-39-9012",
        "url":  "https://www.city.yamaguchi.lg.jp/site/korei/4741.html"
    },
    {
        "id":  1687,
        "prefecture":  "山口県",
        "city":  "山口市",
        "area":  "陶・鋳銭司・名田島・秋穂",
        "name":  "山口市川東地域包括支援センター",
        "tel":  "083-986-2077",
        "url":  "https://www.city.yamaguchi.lg.jp/site/korei/4741.html"
    },
    {
        "id":  1688,
        "prefecture":  "山口県",
        "city":  "山口市",
        "area":  "徳地",
        "name":  "山口市基幹型地域包括支援センター徳地分室",
        "tel":  "0835-52-0670",
        "url":  "https://www.city.yamaguchi.lg.jp/map/korei/7259.html"
    },
    {
        "id":  1689,
        "prefecture":  "山口県",
        "city":  "山口市",
        "area":  "阿東",
        "name":  "山口市基幹型地域包括支援センター阿東分室",
        "tel":  "083-956-0995",
        "url":  "https://www.city.yamaguchi.lg.jp/map/korei/7260.html"
    },
    {
        "id":  1690,
        "prefecture":  "山口県",
        "city":  "山口市",
        "area":  "市内全域",
        "name":  "山口市基幹型地域包括支援センター",
        "tel":  "083-934-2758",
        "url":  "https://www.city.yamaguchi.lg.jp/map/korei/7258.html"
    },
    {
        "id": 2006,
        "prefecture": "山口県",
        "city": "下関市",
        "area": "本庁東部",
        "name": "下関市本庁東部地域包括支援センター",
        "tel": "083-250-6581",
        "url": "https://www.city.shimonoseki.lg.jp/soshiki/40/109338.html"
    },
    {
        "id": 2007,
        "prefecture": "山口県",
        "city": "下関市",
        "area": "本庁西部",
        "name": "下関市本庁西部地域包括支援センター",
        "tel": "083-250-8521",
        "url": "https://www.city.shimonoseki.lg.jp/soshiki/40/109338.html"
    },
    {
        "id": 2008,
        "prefecture": "山口県",
        "city": "下関市",
        "area": "本庁北部",
        "name": "下関市本庁北部地域包括支援センター",
        "tel": "083-255-1111",
        "url": "https://www.city.shimonoseki.lg.jp/soshiki/40/109338.html"
    },
    {
        "id": 2009,
        "prefecture": "山口県",
        "city": "下関市",
        "area": "彦島",
        "name": "下関市彦島地域包括支援センター",
        "tel": "083-266-6516",
        "url": "https://www.city.shimonoseki.lg.jp/soshiki/40/109338.html"
    },
    {
        "id": 2010,
        "prefecture": "山口県",
        "city": "下関市",
        "area": "長府",
        "name": "下関市長府地域包括支援センター",
        "tel": "083-227-3151",
        "url": "https://www.city.shimonoseki.lg.jp/soshiki/40/109338.html"
    },
    {
        "id": 2011,
        "prefecture": "山口県",
        "city": "下関市",
        "area": "王司・清末・小月・吉田・王喜",
        "name": "下関市東部地域包括支援センター",
        "tel": "083-249-2015",
        "url": "https://www.city.shimonoseki.lg.jp/soshiki/40/109338.html"
    },
    {
        "id": 2012,
        "prefecture": "山口県",
        "city": "下関市",
        "area": "川中",
        "name": "下関市川中地域包括支援センター",
        "tel": "083-252-6223",
        "url": "https://www.city.shimonoseki.lg.jp/soshiki/40/109338.html"
    },
    {
        "id": 2013,
        "prefecture": "山口県",
        "city": "下関市",
        "area": "安岡・吉見",
        "name": "下関市安岡・吉見地域包括支援センター",
        "tel": "083-249-5015",
        "url": "https://www.city.shimonoseki.lg.jp/soshiki/40/109338.html"
    },
    {
        "id": 2014,
        "prefecture": "山口県",
        "city": "下関市",
        "area": "勝山・内日",
        "name": "下関市勝山・内日地域包括支援センター",
        "tel": "083-227-2700",
        "url": "https://www.city.shimonoseki.lg.jp/soshiki/40/109338.html"
    },
    {
        "id": 2015,
        "prefecture": "山口県",
        "city": "下関市",
        "area": "菊川・豊田",
        "name": "下関市菊川・豊田地域包括支援センター",
        "tel": "083-287-2870",
        "url": "https://www.city.shimonoseki.lg.jp/soshiki/40/109338.html"
    },
    {
        "id": 2016,
        "prefecture": "山口県",
        "city": "下関市",
        "area": "豊浦",
        "name": "下関市豊浦地域包括支援センター",
        "tel": "083-775-2941",
        "url": "https://www.city.shimonoseki.lg.jp/soshiki/40/109338.html"
    },
    {
        "id": 2017,
        "prefecture": "山口県",
        "city": "下関市",
        "area": "豊北",
        "name": "下関市豊北地域包括支援センター",
        "tel": "083-782-1904",
        "url": "https://www.city.shimonoseki.lg.jp/soshiki/40/109338.html"
    },
    {"id":2187,"prefecture":"山口県","city":"宇部市","area":"東岐波、川上","name":"東部第1地域包括支援センター","tel":"0836-39-6971","url":"https://www.city.ube.yamaguchi.jp/kenkou/koureifukushi/kourei_soudan/1005415/index.html"},
    {"id":2188,"prefecture":"山口県","city":"宇部市","area":"西岐波、常盤","name":"東部第2地域包括支援センター","tel":"0836-39-6151","url":"https://www.city.ube.yamaguchi.jp/kenkou/koureifukushi/kourei_soudan/1005415/index.html"},
    {"id":2189,"prefecture":"山口県","city":"宇部市","area":"西宇部、厚南","name":"西部第1地域包括支援センター","tel":"0836-45-3969","url":"https://www.city.ube.yamaguchi.jp/kenkou/koureifukushi/kourei_soudan/1005415/index.html"},
    {"id":2190,"prefecture":"山口県","city":"宇部市","area":"黒石、原","name":"西部第2地域包括支援センター","tel":"0836-43-9307","url":"https://www.city.ube.yamaguchi.jp/kenkou/koureifukushi/kourei_soudan/1005415/index.html"},
    {"id":2191,"prefecture":"山口県","city":"宇部市","area":"上宇部、小羽山","name":"中部第1地域包括支援センター","tel":"0836-43-9551","url":"https://www.city.ube.yamaguchi.jp/kenkou/koureifukushi/kourei_soudan/1005415/index.html"},
    {"id":2192,"prefecture":"山口県","city":"宇部市","area":"新川、鵜の島、藤山","name":"中部第2地域包括支援センター","tel":"0836-39-6131","url":"https://www.city.ube.yamaguchi.jp/kenkou/koureifukushi/kourei_soudan/1005415/index.html"},
    {"id":2193,"prefecture":"山口県","city":"宇部市","area":"厚東、二俣瀬、小野","name":"北部東地域包括支援センター","tel":"0836-62-5858","url":"https://www.city.ube.yamaguchi.jp/kenkou/koureifukushi/kourei_soudan/1005415/index.html"},
    {"id":2194,"prefecture":"山口県","city":"宇部市","area":"船木、万倉、吉部","name":"北部西地域包括支援センター","tel":"0836-67-0506","url":"https://www.city.ube.yamaguchi.jp/kenkou/koureifukushi/kourei_soudan/1005415/index.html"},
    {"id":2195,"prefecture":"山口県","city":"宇部市","area":"恩田、岬","name":"南部第1地域包括支援センター","tel":"0836-38-8551","url":"https://www.city.ube.yamaguchi.jp/kenkou/koureifukushi/kourei_soudan/1005415/index.html"},
    {"id":2196,"prefecture":"山口県","city":"宇部市","area":"見初、神原、琴芝","name":"南部第2地域包括支援センター","tel":"0836-38-3220","url":"https://www.city.ube.yamaguchi.jp/kenkou/koureifukushi/kourei_soudan/1005415/index.html"},
    {"id":2562,"prefecture":"山口県","city":"周南市","area":"久米・櫛浜・鼓南・熊毛","name":"いきいきさぽーと周南東部","tel":"0834-29-1155","url":"https://kochoen.jp/community_general/"},
    {"id":2563,"prefecture":"山口県","city":"周南市","area":"周陽・桜木・秋月・岐山・大津島","name":"いきいきさぽーとつづみ園","tel":"0834-28-7055","url":"https://www.shunan-jigyodan.jp/service/regional-comprehensive-support/"},
    {"id":2564,"prefecture":"山口県","city":"周南市","area":"遠石・関門・中央・今宿","name":"いきいきさぽーと徳山医師会","tel":"0834-32-9035","url":"http://www.tokuyamaishikai.com/homesupport/office/center.html"},
    {"id":2565,"prefecture":"山口県","city":"周南市","area":"富田・菊川・和田・福川・夜市・戸田・湯野","name":"いきいきさぽーと周南西部","tel":"0834-62-6301","url":"https://www.shunan-shakyo.or.jp/thema03/sougousoudan/"},
    {"id":2566,"prefecture":"山口県","city":"周南市","area":"須々万・長穂・向道・中須・須金・鹿野","name":"いきいきさぽーと周南北部","tel":"0834-87-2000","url":"http://www.kanofukushikai.or.jp/service/regional-support-center/"}
]
